{
    "id": 138290064,
    "name": "Ocean Not Blue",
    "author": "Jumbotony18YT",
    "creators": [1],
    "verifier": "Jumbotony18YT",
    "verification": "https://youtu.be/WXbQ24mrqLE?si=go46BP6NoyJ9fSQk",
    "percentToQualify": "100",
    "password": "Free To Copy",
    "enjoyment": "5",
    "records": [
          {
            "user": "pixelfactorial",
            "link": "https://discord.com/channels/1468169665158053975/1495306784712425603/1495306784712425603",
            "percent": 100,
            "hz": 0
        }
    ]
}
